video_club/__init__.py
video_club/manage.py
video_club/rent_store/__init__.py
video_club/rent_store/admin.py
video_club/rent_store/apps.py
video_club/rent_store/models.py
video_club/rent_store/serializers.py
video_club/rent_store/tests.py
video_club/rent_store/urls.py
video_club/rent_store/views.py
video_club/rent_store/management/__init__.py
video_club/rent_store/migrations/0001_initial.py
video_club/rent_store/migrations/0002_add_categories.py
video_club/rent_store/migrations/0003_add_movies.py
video_club/rent_store/migrations/0004_customuser_wallet.py
video_club/rent_store/migrations/__init__.py
video_club/video_club/__init__.py
video_club/video_club/asgi.py
video_club/video_club/settings.py
video_club/video_club/urls.py
video_club/video_club/wsgi.py
Deustest2022-1.0.dist-info/METADATA
Deustest2022-1.0.dist-info/WHEEL
Deustest2022-1.0.dist-info/top_level.txt
Deustest2022-1.0.dist-info/zip-safe
Deustest2022-1.0.dist-info/RECORD
